discordwrap/Auth/Auth.py
discordwrap/Auth/__init__.py
discordwrap/Errors/Errors.py
discordwrap/Errors/__init__.py
discordwrap/__init__.py
discordwrap/core/__init__.py
discordwrap/core/request.py
discordwrap/methods/__init__.py
discordwrap/methods/channel.py
discordwrap-0.9.0.dist-info/LICENSE
discordwrap-0.9.0.dist-info/METADATA
discordwrap-0.9.0.dist-info/WHEEL
discordwrap-0.9.0.dist-info/RECORD
