Metadata-Version: 2.1
Name: discordwrap
Version: 0.9.0
Summary: A simple, intuitive wrapper around the underbelly of the discord API. This library is meant to be used with the discord docs. Responses from methods in the library will return JSON just as discords api details.
Home-page: https://discordwrap.brunuslabs.com/
License: MIT
Keywords: Discord,API,Lightweight,AsyncIO
Author: josh
Author-email: josh@brunuslabs.com
Requires-Python: >=3.10,<4.0
Classifier: Framework :: AsyncIO
Classifier: License :: OSI Approved :: MIT License
Classifier: Operating System :: OS Independent
Classifier: Programming Language :: Python :: 3
Classifier: Programming Language :: Python :: 3.10
Classifier: Programming Language :: Python :: 3.11
Classifier: Programming Language :: Python :: 3
Classifier: Topic :: Internet
Classifier: Topic :: Software Development :: Libraries
Classifier: Topic :: Software Development :: Libraries :: Python Modules
Project-URL: Documentation, https://discordwrap.brunuslabs.com/
Project-URL: Repository, https://github.com/Brunus-Labs/discordwrap
